envcast/__init__.py
envcast/base.py
envcast/exceptions.py
envcast/py.typed
envcast/tests/__init__.py
envcast/tests/test_base.py
envcast-1.2.0.dist-info/LICENSE
envcast-1.2.0.dist-info/WHEEL
envcast-1.2.0.dist-info/METADATA
envcast-1.2.0.dist-info/RECORD
