Metadata-Version: 2.1
Name: envcast
Version: 1.2.0
Summary: This module helps to cast environment variables to desired types. It may be very useful for 12factor app usage.
Home-page: https://github.com/xfenix/envcast/
License: MIT
Author: Denis Anikin
Author-email: ad@xfenix.ru
Requires-Python: >=3.7,<4.0
Classifier: License :: OSI Approved :: MIT License
Classifier: Programming Language :: Python :: 3
Classifier: Programming Language :: Python :: 3.10
Classifier: Programming Language :: Python :: 3.7
Classifier: Programming Language :: Python :: 3.8
Classifier: Programming Language :: Python :: 3.9
Classifier: Topic :: Software Development :: Libraries :: Python Modules
Project-URL: Documentation, https://github.com/xfenix/envcast#envcast
